Workbook

Sheet Leia-me
A1: Unit economics: app de mobilidade (modelo de simulação de take rate)
A3: Objetivo | B3: Testar quanto uma plataforma ganha por corrida e quanto sobra ao motorista em diferentes comissões (take rate), e quantas corridas por mês cobrem o custo fixo de uma cidade.
A4: Como usar | B4: Edite só as células com texto azul na aba Premissas (e os cabeçalhos azuis da aba Simulação). Todo o resto é fórmula e recalcula.
A5: Legenda | B5: Azul = dado que você edita. Preto = fórmula. Verde = link para outra aba. Fundo amarelo = premissa-chave.
A6: Abas | B6: Premissas: entradas. Por corrida: comparação de 5 cenários de take rate. Simulação: varredura de 0% a 40% com gráficos e grade take rate x ticket.
A7: Aviso importante | B7: Ticket, km, tempo por corrida e todos os custos da plataforma são PREMISSAS ILUSTRATIVAS minhas, não dados medidos. Substitua por números reais da sua cidade-piloto antes de usar o resultado em qualquer decisão.
A8: Fontes | B8: Custo por km do motorista: Rota do Motorista (SP, 3.200 km/mês). Take rate 40%: Garagem360, nov/2025 (relatos de 40–50%, picos acima de 60%). Take rate 25%: Vida de Motorista (meta da Uber, fonte secundária). Teto de 30%: debate do PLP 152/2025 (Estado de Minas, abr/2026). Take rate de apps alternativos: MobizapSP 10,95% (Tecnoblog), Bibi Mob 5% (Tecnoblog).
A9: Limitações | B9: O modelo é por corrida e mensal simples. Não inclui CAC, churn, curva de adoção, impostos sobre a receita nem custos de tecnologia além do custo fixo mensal informado.

Sheet Premissas
A1: Premissas (edite as células azuis)
A3: Premissa | B3: Valor | C3: Unidade | D3: Fonte / nota
A4: Tarifa média paga pelo passageiro | B4: 35 | C4: R$/corrida | D4: Premissa ilustrativa. Substituir pelo ticket real da cidade-piloto.
A5: Distância paga por corrida | B5: 9 | C5: km | D5: Premissa ilustrativa.
A6: Km ocioso (deslocamento até o passageiro e espera) | B6: 0.25 | C6: % sobre km pagos | D6: Premissa ilustrativa.
A7: Custo operacional do motorista | B7: 1.71 | C7: R$/km | D7: Rota do Motorista: R$ 1,71/km em SP (R$ 5.460/mês, 3.200 km). Inclui combustível, depreciação, seguro, limpeza. Cidades menores: R$ 0,90–1,10.
A8: Tempo por corrida, incluindo espera | B8: 28 | C8: minutos | D8: Premissa ilustrativa.
A9: Horas trabalhadas por mês | B9: 160 | C9: horas | D9: Premissa ilustrativa (8 h x 20 dias).
A10: Processamento de pagamento | B10: 0.03 | C10: % do ticket | D10: Premissa ilustrativa.
A11: Suporte, seguro e segurança | B11: 0.8 | C11: R$/corrida | D11: Premissa ilustrativa.
A12: Incentivo ao motorista | B12: 0.5 | C12: R$/corrida | D12: Premissa ilustrativa (bônus de retenção). Somado ao ganho do motorista.
A13: Custo fixo mensal por cidade | B13: 300000 | C13: R$/mês | D13: Premissa ilustrativa: equipe local, marketing, infraestrutura.
A14: Take rate: incumbente, relatos altos | B14: 0.4 | C14: % do ticket | D14: Garagem360, nov/2025: retenção média de 40–50%.
A15: Take rate: incumbente, meta declarada | B15: 0.25 | C15: % do ticket | D15: Vida de Motorista: Uber mira cerca de 25% (fonte secundária).
... A18: Take rate: nosso cenário agressivo | B18: 0.08 | C18: % do ticket | D18: Hipótese. Referência: Bibi Mob 5%.

Sheet Por corrida
A1: Economia por corrida: cinco cenários de take rate
A3: Linha | B3: Incumbente (relatos altos) | C3: Incumbente (meta) | D3: Teto do PLP | E3: Nosso: base | F3: Nosso: agressivo
A4: Take rate | B4: =Premissas!$B$14 -> 0.4 | C4: =Premissas!$B$15 -> 0.25 | D4: =Premissas!$B$16 -> 0.3 | E4: =Premissas!$B$17 -> 0.12 | F4: =Premissas!$B$18 -> 0.08
A5: Tarifa do passageiro (R$) | B5: =Premissas!$B$4 -> 35 | C5: =Premissas!$B$4 -> 35 | D5: =Premissas!$B$4 -> 35 | E5: =Premissas!$B$4 -> 35 | F5: =Premissas!$B$4 -> 35
A6: Plataforma: receita por corrida (R$) | B6: =B5*B4 -> 14 | C6: =C5*C4 -> 8.75 | D6: =D5*D4 -> 10.5 | E6: =E5*E4 -> 4.2 | F6: =F5*F4 -> 2.8
A7: Plataforma: processamento de pagamento (R$) | B7: =B5*Premissas!$B$10 -> 1.05 | C7: =C5*Premissas!$B$10 -> 1.05 | D7: =D5*Premissas!$B$10 -> 1.05 | E7: =E5*Premissas!$B$10 -> 1.05 | F7: =F5*Premissas!$B$10 -> 1.05
A8: Plataforma: suporte, seguro e segurança (R$) | B8: =Premissas!$B$11 -> 0.8 | C8: =Premissas!$B$11 -> 0.8 | D8: =Premissas!$B$11 -> 0.8 | E8: =Premissas!$B$11 -> 0.8 | F8: =Premissas!$B$11 -> 0.8
A9: Plataforma: incentivo ao motorista (R$) | B9: =Premissas!$B$12 -> 0.5 | C9: =Premissas!$B$12 -> 0.5 | D9: =Premissas!$B$12 -> 0.5 | E9: =Premissas!$B$12 -> 0.5 | F9: =Premissas!$B$12 -> 0.5
A10: Plataforma: margem de contribuição (R$/corrida) | B10: =B6-B7-B8-B9 -> 11.65 | C10: =C6-C7-C8-C9 -> 6.4 | D10: =D6-D7-D8-D9 -> 8.15 | E10: =E6-E7-E8-E9 -> 1.85 | F10: =F6-F7-F8-F9 -> 0.45
A11: Plataforma: margem sobre o ticket | B11: =IF(B5>0,B10/B5,0) -> 0.33285714 | C11: =IF(C5>0,C10/C5,0) -> 0.18285714 | D11: =IF(D5>0,D10/D5,0) -> 0.23285714 | E11: =IF(E5>0,E10/E5,0) -> 0.052857143 | F11: =IF(F5>0,F10/F5,0) -> 0.012857143
A12: Motorista
A13: Motorista: ganho bruto da corrida (R$) | B13: =B5-B6 -> 21 | C13: =C5-C6 -> 26.25 | D13: =D5-D6 -> 24.5 | E13: =E5-E6 -> 30.8 | F13: =F5-F6 -> 32.2
A14: Motorista: km totais rodados | B14: =Premissas!$B$5*(1+Premissas!$B$6) -> 11.25 | C14: =Premissas!$B$5*(1+Premissas!$B$6) -> 11.25 | D14: =Premissas!$B$5*(1+Premissas!$B$6) -> 11.25 | E14: =Premissas!$B$5*(1+Premissas!$B$6) -> 11.25 | F14: =Premissas!$B$5*(1+Premissas!$B$6) -> 11.25
A15: Motorista: custo operacional (R$) | B15: =B14*Premissas!$B$7 -> 19.2375 | C15: =C14*Premissas!$B$7 -> 19.2375 | D15: =D14*Premissas!$B$7 -> 19.2375 | E15: =E14*Premissas!$B$7 -> 19.2375 | F15: =F14*Premissas!$B$7 -> 19.2375
A16: Motorista: ganho líquido por corrida, com incentivo (R$) | B16: =B13-B15+B9 -> 2.2625 | C16: =C13-C15+C9 -> 7.5125 | D16: =D13-D15+D9 -> 5.7625 | E16: =E13-E15+E9 -> 12.0625 | F16: =F13-F15+F9 -> 13.4625
A17: Motorista: corridas por hora | B17: =60/Premissas!$B$8 -> 2.1428571 | C17: =60/Premissas!$B$8 -> 2.1428571 | D17: =60/Premissas!$B$8 -> 2.1428571 | E17: =60/Premissas!$B$8 -> 2.1428571 | F17: =60/Premissas!$B$8 -> 2.1428571
A18: Motorista: ganho líquido por hora (R$/h) | B18: =B16*B17 -> 4.8482143 | C18: =C16*C17 -> 16.098214 | D18: =D16*D17 -> 12.348214 | E18: =E16*E17 -> 25.848214 | F18: =F16*F17 -> 28.848214
A19: Motorista: ganho líquido por mês (R$) | B19: =B18*Premissas!$B$9 -> 775.71429 | C19: =C18*Premissas!$B$9 -> 2575.7143 | D19: =D18*Premissas!$B$9 -> 1975.7143 | E19: =E18*Premissas!$B$9 -> 4135.7143 | F19: =F18*Premissas!$B$9 -> 4615.7143
A20: Motorista: diferença por hora vs incumbente (meta) | B20: =B18-$C$18 -> -11.25 | C20: =C18-$C$18 -> 0 | D20: =D18-$C$18 -> -3.75 | E20: =E18-$C$18 -> 9.75 | F20: =F18-$C$18 -> 12.75
A21: Escala para empatar (custo fixo de uma cidade)
A22: Corridas por mês para cobrir o custo fixo | B22: =IF(B10>0,Premissas!$B$13/B10,"Sem margem") -> 25751.073 | C22: =IF(C10>0,Premissas!$B$13/C10,"Sem margem") -> 46875 | D22: =IF(D10>0,Premissas!$B$13/D10,"Sem margem") -> 36809.816 | E22: =IF(E10>0,Premissas!$B$13/E10,"Sem margem") -> 162162.16 | F22: =IF(F10>0,Premissas!$B$13/F10,"Sem margem") -> 666666.67
A23: Corridas por dia (mês de 30 dias) | B23: =IF(ISNUMBER(B22),B22/30,"Sem margem") -> 858.3691 | C23: =IF(ISNUMBER(C22),C22/30,"Sem margem") -> 1562.5 | D23: =IF(ISNUMBER(D22),D22/30,"Sem margem") -> 1226.9939 | E23: =IF(ISNUMBER(E22),E22/30,"Sem margem") -> 5405.4054 | F23: =IF(ISNUMBER(F22),F22/30,"Sem margem") -> 22222.222
A24: Motoristas ativos necessários | B24: =IF(ISNUMBER(B22),B22/(B17*Premissas!$B$9),"Sem margem") -> 75.107296 | C24: =IF(ISNUMBER(C22),C22/(C17*Premissas!$B$9),"Sem margem") -> 136.71875 | D24: =IF(ISNUMBER(D22),D22/(D17*Premissas!$B$9),"Sem margem") -> 107.36196 | E24: =IF(ISNUMBER(E22),E22/(E17*Premissas!$B$9),"Sem margem") -> 472.97297 | F24: =IF(ISNUMBER(F22),F22/(F17*Premissas!$B$9),"Sem margem") -> 1944.4444
A26: Linha 20 compara o ganho por hora de cada cenário com a coluna 'Incumbente (meta)'. Valores baseados nas premissas ilustrativas da aba Premissas.

Sheet Simulação
A1: Varredura de take rate de 0% a 40%
A3: Take rate | B3: Receita da plataforma (R$/corrida) | C3: Margem de contribuição (R$/corrida) | D3: Ganho líquido do motorista (R$/h) | E3: Corridas/mês para empatar | F3: Motoristas ativos necessários
A4: 0 | B4: =Premissas!$B$4*A4 -> 0 | C4: =B4-Premissas!$B$4*Premissas!$B$10-Premissas!$B$11-Premissas!$B$12 -> -2.35 | D4: =((Premissas!$B$4*(1-A4))-Premissas!$B$5*(1+Premissas!$B$6)*Premissas!$B$7+Premissas!$B$12)*(60/Premissas!$B$8) -> 34.848214 | E4: =IF(C4>0,Premissas!$B$13/C4,"Sem margem") -> Sem margem | F4: =IF(ISNUMBER(E4),E4/((60/Premissas!$B$8)*Premissas!$B$9),"Sem margem") -> Sem margem
A5: 0.025 | B5: =Premissas!$B$4*A5 -> 0.875 | C5: =B5-Premissas!$B$4*Premissas!$B$10-Premissas!$B$11-Premissas!$B$12 -> -1.475 | D5: =((Premissas!$B$4*(1-A5))-Premissas!$B$5*(1+Premissas!$B$6)*Premissas!$B$7+Premissas!$B$12)*(60/Premissas!$B$8) -> 32.973214 | E5: =IF(C5>0,Premissas!$B$13/C5,"Sem margem") -> Sem margem | F5: =IF(ISNUMBER(E5),E5/((60/Premissas!$B$8)*Premissas!$B$9),"Sem margem") -> Sem margem
A6: 0.05 | B6: =Premissas!$B$4*A6 -> 1.75 | C6: =B6-Premissas!$B$4*Premissas!$B$10-Premissas!$B$11-Premissas!$B$12 -> -0.6 | D6: =((Premissas!$B$4*(1-A6))-Premissas!$B$5*(1+Premissas!$B$6)*Premissas!$B$7+Premissas!$B$12)*(60/Premissas!$B$8) -> 31.098214 | E6: =IF(C6>0,Premissas!$B$13/C6,"Sem margem") -> Sem margem | F6: =IF(ISNUMBER(E6),E6/((60/Premissas!$B$8)*Premissas!$B$9),"Sem margem") -> Sem margem
A7: 0.075 | B7: =Premissas!$B$4*A7 -> 2.625 | C7: =B7-Premissas!$B$4*Premissas!$B$10-Premissas!$B$11-Premissas!$B$12 -> 0.275 | D7: =((Premissas!$B$4*(1-A7))-Premissas!$B$5*(1+Premissas!$B$6)*Premissas!$B$7+Premissas!$B$12)*(60/Premissas!$B$8) -> 29.223214 | E7: =IF(C7>0,Premissas!$B$13/C7,"Sem margem") -> 1090909.1 | F7: =IF(ISNUMBER(E7),E7/((60/Premissas!$B$8)*Premissas!$B$9),"Sem margem") -> 3181.8182
A8: 0.1 | B8: =Premissas!$B$4*A8 -> 3.5 | C8: =B8-Premissas!$B$4*Premissas!$B$10-Premissas!$B$11-Premissas!$B$12 -> 1.15 | D8: =((Premissas!$B$4*(1-A8))-Premissas!$B$5*(1+Premissas!$B$6)*Premissas!$B$7+Premissas!$B$12)*(60/Premissas!$B$8) -> 27.348214 | E8: =IF(C8>0,Premissas!$B$13/C8,"Sem margem") -> 260869.57 | F8: =IF(ISNUMBER(E8),E8/((60/Premissas!$B$8)*Premissas!$B$9),"Sem margem") -> 760.86957
A9: 0.125 | B9: =Premissas!$B$4*A9 -> 4.375 | C9: =B9-Premissas!$B$4*Premissas!$B$10-Premissas!$B$11-Premissas!$B$12 -> 2.025 | D9: =((Premissas!$B$4*(1-A9))-Premissas!$B$5*(1+Premissas!$B$6)*Premissas!$B$7+Premissas!$B$12)*(60/Premissas!$B$8) -> 25.473214 | E9: =IF(C9>0,Premissas!$B$13/C9,"Sem margem") -> 148148.15 | F9: =IF(ISNUMBER(E9),E9/((60/Premissas!$B$8)*Premissas!$B$9),"Sem margem") -> 432.09877
A10: 0.15 | B10: =Premissas!$B$4*A10 -> 5.25 | C10: =B10-Premissas!$B$4*Premissas!$B$10-Premissas!$B$11-Premissas!$B$12 -> 2.9 | D10: =((Premissas!$B$4*(1-A10))-Premissas!$B$5*(1+Premissas!$B$6)*Premissas!$B$7+Premissas!$B$12)*(60/Premissas!$B$8) -> 23.598214 | E10: =IF(C10>0,Premissas!$B$13/C10,"Sem margem") -> 103448.28 | F10: =IF(ISNUMBER(E10),E10/((60/Premissas!$B$8)*Premissas!$B$9),"Sem margem") -> 301.72414
A11: 0.175 | B11: =Premissas!$B$4*A11 -> 6.125 | C11: =B11-Premissas!$B$4*Premissas!$B$10-Premissas!$B$11-Premissas!$B$12 -> 3.775 | D11: =((Premissas!$B$4*(1-A11))-Premissas!$B$5*(1+Premissas!$B$6)*Premissas!$B$7+Premissas!$B$12)*(60/Premissas!$B$8) -> 21.723214 | E11: =IF(C11>0,Premissas!$B$13/C11,"Sem margem") -> 79470.199 | F11: =IF(ISNUMBER(E11),E11/((60/Premissas!$B$8)*Premissas!$B$9),"Sem margem") -> 231.78808
A12: 0.2 | B12: =Premissas!$B$4*A12 -> 7 | C12: =B12-Premissas!$B$4*Premissas!$B$10-Premissas!$B$11-Premissas!$B$12 -> 4.65 | D12: =((Premissas!$B$4*(1-A12))-Premissas!$B$5*(1+Premissas!$B$6)*Premissas!$B$7+Premissas!$B$12)*(60/Premissas!$B$8) -> 19.848214 | E12: =IF(C12>0,Premissas!$B$13/C12,"Sem margem") -> 64516.129 | F12: =IF(ISNUMBER(E12),E12/((60/Premissas!$B$8)*Premissas!$B$9),"Sem margem") -> 188.17204
A13: 0.225 | B13: =Premissas!$B$4*A13 -> 7.875 | C13: =B13-Premissas!$B$4*Premissas!$B$10-Premissas!$B$11-Premissas!$B$12 -> 5.525 | D13: =((Premissas!$B$4*(1-A13))-Premissas!$B$5*(1+Premissas!$B$6)*Premissas!$B$7+Premissas!$B$12)*(60/Premissas!$B$8) -> 17.973214 | E13: =IF(C13>0,Premissas!$B$13/C13,"Sem margem") -> 54298.643 | F13: =IF(ISNUMBER(E13),E13/((60/Premissas!$B$8)*Premissas!$B$9),"Sem margem") -> 158.37104
A14: 0.25 | B14: =Premissas!$B$4*A14 -> 8.75 | C14: =B14-Premissas!$B$4*Premissas!$B$10-Premissas!$B$11-Premissas!$B$12 -> 6.4 | D14: =((Premissas!$B$4*(1-A14))-Premissas!$B$5*(1+Premissas!$B$6)*Premissas!$B$7+Premissas!$B$12)*(60/Premissas!$B$8) -> 16.098214 | E14: =IF(C14>0,Premissas!$B$13/C14,"Sem margem") -> 46875 | F14: =IF(ISNUMBER(E14),E14/((60/Premissas!$B$8)*Premissas!$B$9),"Sem margem") -> 136.71875
A15: 0.275 | B15: =Premissas!$B$4*A15 -> 9.625 | C15: =B15-Premissas!$B$4*Premissas!$B$10-Premissas!$B$11-Premissas!$B$12 -> 7.275 | D15: =((Premissas!$B$4*(1-A15))-Premissas!$B$5*(1+Premissas!$B$6)*Premissas!$B$7+Premissas!$B$12)*(60/Premissas!$B$8) -> 14.223214 | E15: =IF(C15>0,Premissas!$B$13/C15,"Sem margem") -> 41237.113 | F15: =IF(ISNUMBER(E15),E15/((60/Premissas!$B$8)*Premissas!$B$9),"Sem margem") -> 120.27491
... A20: 0.4 | B20: =Premissas!$B$4*A20 -> 14 | C20: =B20-Premissas!$B$4*Premissas!$B$10-Premissas!$B$11-Premissas!$B$12 -> 11.65 | D20: =((Premissas!$B$4*(1-A20))-Premissas!$B$5*(1+Premissas!$B$6)*Premissas!$B$7+Premissas!$B$12)*(60/Premissas!$B$8) -> 4.8482143 | E20: =IF(C20>0,Premissas!$B$13/C20,"Sem margem") -> 25751.073 | F20: =IF(ISNUMBER(E20),E20/((60/Premissas!$B$8)*Premissas!$B$9),"Sem margem") -> 75.107296
A23: Margem de contribuição (R$/corrida): take rate x ticket
A24: Take rate \ Ticket (R$) | B24: 25 | C24: 30 | D24: 35 | E24: 40 | F24: 45
A25: 0.05 | B25: =B$24*($A25-Premissas!$B$10)-Premissas!$B$11-Premissas!$B$12 -> -0.8 | C25: =C$24*($A25-Premissas!$B$10)-Premissas!$B$11-Premissas!$B$12 -> -0.7 | D25: =D$24*($A25-Premissas!$B$10)-Premissas!$B$11-Premissas!$B$12 -> -0.6 | E25: =E$24*($A25-Premissas!$B$10)-Premissas!$B$11-Premissas!$B$12 -> -0.5 | F25: =F$24*($A25-Premissas!$B$10)-Premissas!$B$11-Premissas!$B$12 -> -0.4
A26: 0.08 | B26: =B$24*($A26-Premissas!$B$10)-Premissas!$B$11-Premissas!$B$12 -> -0.05 | C26: =C$24*($A26-Premissas!$B$10)-Premissas!$B$11-Premissas!$B$12 -> 0.2 | D26: =D$24*($A26-Premissas!$B$10)-Premissas!$B$11-Premissas!$B$12 -> 0.45 | E26: =E$24*($A26-Premissas!$B$10)-Premissas!$B$11-Premissas!$B$12 -> 0.7 | F26: =F$24*($A26-Premissas!$B$10)-Premissas!$B$11-Premissas!$B$12 -> 0.95
A27: 0.1 | B27: =B$24*($A27-Premissas!$B$10)-Premissas!$B$11-Premissas!$B$12 -> 0.45 | C27: =C$24*($A27-Premissas!$B$10)-Premissas!$B$11-Premissas!$B$12 -> 0.8 | D27: =D$24*($A27-Premissas!$B$10)-Premissas!$B$11-Premissas!$B$12 -> 1.15 | E27: =E$24*($A27-Premissas!$B$10)-Premissas!$B$11-Premissas!$B$12 -> 1.5 | F27: =F$24*($A27-Premissas!$B$10)-Premissas!$B$11-Premissas!$B$12 -> 1.85
A28: 0.12 | B28: =B$24*($A28-Premissas!$B$10)-Premissas!$B$11-Premissas!$B$12 -> 0.95 | C28: =C$24*($A28-Premissas!$B$10)-Premissas!$B$11-Premissas!$B$12 -> 1.4 | D28: =D$24*($A28-Premissas!$B$10)-Premissas!$B$11-Premissas!$B$12 -> 1.85 | E28: =E$24*($A28-Premissas!$B$10)-Premissas!$B$11-Premissas!$B$12 -> 2.3 | F28: =F$24*($A28-Premissas!$B$10)-Premissas!$B$11-Premissas!$B$12 -> 2.75
A29: 0.15 | B29: =B$24*($A29-Premissas!$B$10)-Premissas!$B$11-Premissas!$B$12 -> 1.7 | C29: =C$24*($A29-Premissas!$B$10)-Premissas!$B$11-Premissas!$B$12 -> 2.3 | D29: =D$24*($A29-Premissas!$B$10)-Premissas!$B$11-Premissas!$B$12 -> 2.9 | E29: =E$24*($A29-Premissas!$B$10)-Premissas!$B$11-Premissas!$B$12 -> 3.5 | F29: =F$24*($A29-Premissas!$B$10)-Premissas!$B$11-Premissas!$B$12 -> 4.1
A30: 0.2 | B30: =B$24*($A30-Premissas!$B$10)-Premissas!$B$11-Premissas!$B$12 -> 2.95 | C30: =C$24*($A30-Premissas!$B$10)-Premissas!$B$11-Premissas!$B$12 -> 3.8 | D30: =D$24*($A30-Premissas!$B$10)-Premissas!$B$11-Premissas!$B$12 -> 4.65 | E30: =E$24*($A30-Premissas!$B$10)-Premissas!$B$11-Premissas!$B$12 -> 5.5 | F30: =F$24*($A30-Premissas!$B$10)-Premissas!$B$11-Premissas!$B$12 -> 6.35
A31: 0.25 | B31: =B$24*($A31-Premissas!$B$10)-Premissas!$B$11-Premissas!$B$12 -> 4.2 | C31: =C$24*($A31-Premissas!$B$10)-Premissas!$B$11-Premissas!$B$12 -> 5.3 | D31: =D$24*($A31-Premissas!$B$10)-Premissas!$B$11-Premissas!$B$12 -> 6.4 | E31: =E$24*($A31-Premissas!$B$10)-Premissas!$B$11-Premissas!$B$12 -> 7.5 | F31: =F$24*($A31-Premissas!$B$10)-Premissas!$B$11-Premissas!$B$12 -> 8.6
A32: 0.3 | B32: =B$24*($A32-Premissas!$B$10)-Premissas!$B$11-Premissas!$B$12 -> 5.45 | C32: =C$24*($A32-Premissas!$B$10)-Premissas!$B$11-Premissas!$B$12 -> 6.8 | D32: =D$24*($A32-Premissas!$B$10)-Premissas!$B$11-Premissas!$B$12 -> 8.15 | E32: =E$24*($A32-Premissas!$B$10)-Premissas!$B$11-Premissas!$B$12 -> 9.5 | F32: =F$24*($A32-Premissas!$B$10)-Premissas!$B$11-Premissas!$B$12 -> 10.85
A34: Valores negativos aparecem entre parênteses: a corrida perde dinheiro na margem de contribuição.
